{
  "1337":     [
    {
      "question": "What is included in the definition of a group?",
      "options": [
        "Associativity, an inverse element under an operation and a neutral element",
        "Commutativity, an inverse element under an operation and a neutral element",
        "Distributivity, an inverse element under an operation and a neutral element"
      ],
      "structure": "group",
      "type": "multiplechoice",
      "hint": "You don't need one.",
      "difficulty": "easy"
    }
          ]

}